{"appleSKU":"20112018","appleTeamID":"YDT726J7SH","enableCodelessAutoInitialization":true,"products":[{"id":"ballblast.product.remove.ads","type":1,"storeIDs":[],"defaultDescription":{"googleLocale":4,"title":"Remove Ads","description":"Remove Ads"},"screenshotPath":"/Users/kienvuong/Desktop/Screen Shot 2018-11-20 at 10.06.01 PM.png","applePriceTier":2,"xiaomiPriceTier":0,"googlePrice":{"data":[199,0,0,131072],"num":1.99},"pricingTemplateID":"","descriptions":[],"payouts":[]},{"id":"ballblast.package.coin.1","type":0,"storeIDs":[],"defaultDescription":{"googleLocale":4,"title":"Get 1500000 coins","description":"Get 1500000 coins"},"screenshotPath":"/Users/kienvuong/Desktop/Screen Shot 2018-11-20 at 10.01.06 PM.png","applePriceTier":50,"xiaomiPriceTier":0,"googlePrice":{"data":[4999,0,0,131072],"num":49.99},"pricingTemplateID":"","descriptions":[],"payouts":[]},{"id":"ballblast.package.coin.2","type":0,"storeIDs":[],"defaultDescription":{"googleLocale":4,"title":"Get 500000 coins","description":"Get 500000 coins"},"screenshotPath":"/Users/kienvuong/Desktop/Screen Shot 2018-11-20 at 10.01.06 PM.png","applePriceTier":25,"xiaomiPriceTier":0,"googlePrice":{"data":[2499,0,0,131072],"num":24.99},"pricingTemplateID":"","descriptions":[],"payouts":[]},{"id":"ballblast.package.coin.3","type":0,"storeIDs":[],"defaultDescription":{"googleLocale":4,"title":"Get 60000 coins","description":"Get 60000 coins"},"screenshotPath":"/Users/kienvuong/Desktop/Screen Shot 2018-11-20 at 10.01.06 PM.png","applePriceTier":5,"xiaomiPriceTier":0,"googlePrice":{"data":[499,0,0,131072],"num":4.99},"pricingTemplateID":"","descriptions":[],"payouts":[]},{"id":"ballblast.package.coin.4","type":0,"storeIDs":[],"defaultDescription":{"googleLocale":4,"title":"Get 20000 coins","description":"Get 20000 coins"},"screenshotPath":"/Users/kienvuong/Desktop/Screen Shot 2018-11-20 at 10.01.06 PM.png","applePriceTier":3,"xiaomiPriceTier":0,"googlePrice":{"data":[299,0,0,131072],"num":2.99},"pricingTemplateID":"","descriptions":[],"payouts":[]},{"id":"ballblast.package.coin.5","type":0,"storeIDs":[],"defaultDescription":{"googleLocale":4,"title":"Get 3000 coins","description":"Get 3000 coins"},"screenshotPath":"/Users/kienvuong/Desktop/Screen Shot 2018-11-20 at 10.01.06 PM.png","applePriceTier":1,"xiaomiPriceTier":0,"googlePrice":{"data":[99,0,0,131072],"num":0.99},"pricingTemplateID":"","descriptions":[],"payouts":[]},{"id":"ballblast.package.cannon.3","type":0,"storeIDs":[],"defaultDescription":{"googleLocale":4,"title":"Buy canon 3","description":"Buy canon 3"},"screenshotPath":"/Users/kienvuong/Desktop/Screen Shot 2018-11-20 at 10.07.40 PM.png","applePriceTier":3,"xiaomiPriceTier":0,"googlePrice":{"data":[299,0,0,131072],"num":2.99},"pricingTemplateID":"","descriptions":[],"payouts":[]},{"id":"ballblast.package.cannon.4","type":0,"storeIDs":[],"defaultDescription":{"googleLocale":4,"title":"Buy canon 4","description":"Buy canon 4"},"screenshotPath":"/Users/kienvuong/Desktop/Screen Shot 2018-11-20 at 10.07.40 PM.png","applePriceTier":4,"xiaomiPriceTier":0,"googlePrice":{"data":[399,0,0,131072],"num":3.99},"pricingTemplateID":"","descriptions":[],"payouts":[]},{"id":"ballblast.package.cannon.5","type":0,"storeIDs":[],"defaultDescription":{"googleLocale":4,"title":"Buy canon 5","description":"Buy canon 5"},"screenshotPath":"/Users/kienvuong/Desktop/Screen Shot 2018-11-20 at 10.07.40 PM.png","applePriceTier":4,"xiaomiPriceTier":0,"googlePrice":{"data":[399,0,0,131072],"num":3.99},"pricingTemplateID":"","descriptions":[],"payouts":[]},{"id":"ballblast.package.cannon.6","type":0,"storeIDs":[],"defaultDescription":{"googleLocale":4,"title":"Buy canon 6","description":"Buy canon 6"},"screenshotPath":"/Users/kienvuong/Desktop/Screen Shot 2018-11-20 at 10.07.40 PM.png","applePriceTier":4,"xiaomiPriceTier":0,"googlePrice":{"data":[399,0,0,131072],"num":3.99},"pricingTemplateID":"","descriptions":[],"payouts":[]},{"id":"ballblast.package.offer.1","type":0,"storeIDs":[],"defaultDescription":{"googleLocale":4,"title":"Offer","description":"Offer"},"screenshotPath":"/Users/kienvuong/Desktop/Screen Shot 2018-11-20 at 10.04.36 PM.png","applePriceTier":5,"xiaomiPriceTier":0,"googlePrice":{"data":[499,0,0,131072],"num":4.99},"pricingTemplateID":"","descriptions":[],"payouts":[]},{"id":"ballblast.package.offer.1.normal","type":0,"storeIDs":[],"defaultDescription":{"googleLocale":4,"title":"Offer","description":"Offer"},"screenshotPath":"/Users/kienvuong/Desktop/Screen Shot 2018-11-20 at 10.04.36 PM.png","applePriceTier":7,"xiaomiPriceTier":0,"googlePrice":{"data":[699,0,0,131072],"num":6.99},"pricingTemplateID":"","descriptions":[],"payouts":[]},{"id":"ballblast.package.combo.1","type":0,"storeIDs":[],"defaultDescription":{"googleLocale":4,"title":"Combo 1","description":"Combo 1"},"screenshotPath":"/Users/kienvuong/Desktop/Screen Shot 2018-11-20 at 10.01.18 PM.png","applePriceTier":30,"xiaomiPriceTier":0,"googlePrice":{"data":[30,0,0,0],"num":30.0},"pricingTemplateID":"","descriptions":[],"payouts":[]},{"id":"ballblast.package.combo.2","type":0,"storeIDs":[],"defaultDescription":{"googleLocale":4,"title":"Combo 2","description":"Combo 2"},"screenshotPath":"/Users/kienvuong/Desktop/Screen Shot 2018-11-20 at 10.01.18 PM.png","applePriceTier":10,"xiaomiPriceTier":0,"googlePrice":{"data":[10,0,0,0],"num":10.0},"pricingTemplateID":"","descriptions":[],"payouts":[]},{"id":"ballblast.package.combo.3","type":0,"storeIDs":[],"defaultDescription":{"googleLocale":4,"title":"Combo 3","description":"Combo 3"},"screenshotPath":"/Users/kienvuong/Desktop/Screen Shot 2018-11-20 at 10.01.18 PM.png","applePriceTier":10,"xiaomiPriceTier":0,"googlePrice":{"data":[10,0,0,0],"num":10.0},"pricingTemplateID":"","descriptions":[],"payouts":[]},{"id":"ballblast.package.combo.4","type":0,"storeIDs":[],"defaultDescription":{"googleLocale":4,"title":"Combo 4","description":"Combo 4"},"screenshotPath":"/Users/kienvuong/Desktop/Screen Shot 2018-11-20 at 10.01.18 PM.png","applePriceTier":10,"xiaomiPriceTier":0,"googlePrice":{"data":[10,0,0,0],"num":10.0},"pricingTemplateID":"","descriptions":[],"payouts":[]},{"id":"ballblast.package.combo.5","type":0,"storeIDs":[],"defaultDescription":{"googleLocale":4,"title":"Combo 5","description":"Combo 5"},"screenshotPath":"/Users/kienvuong/Desktop/Screen Shot 2018-11-20 at 10.01.18 PM.png","applePriceTier":10,"xiaomiPriceTier":0,"googlePrice":{"data":[10,0,0,0],"num":10.0},"pricingTemplateID":"","descriptions":[],"payouts":[]}]}